LICENSE
NOTICE
mkdocs_python_classy/__init__.py
mkdocs_python_classy/constants.py
mkdocs_python_classy/css/classy.css
mkdocs_python_classy/inspector.py
mkdocs_python_classy/utils.py
mkdocs_python_classy-0.1.3.dist-info/LICENSE
mkdocs_python_classy-0.1.3.dist-info/METADATA
mkdocs_python_classy-0.1.3.dist-info/WHEEL
mkdocs_python_classy-0.1.3.dist-info/entry_points.txt
mkdocs_python_classy-0.1.3.dist-info/RECORD
