Metadata-Version: 2.1
Name: mkdocs-python-classy
Version: 0.1.3
Summary: Mkdocs plugin to view Python Classes.
License: Apache
Keywords: mkdocs
Author: Ken Celenza
Author-email: ken@celenza.org
Requires-Python: >=3.8,<4.0
Classifier: Development Status :: 5 - Production/Stable
Classifier: Intended Audience :: Developers
Classifier: License :: Other/Proprietary License
Classifier: Programming Language :: Python :: 3
Classifier: Programming Language :: Python :: 3.8
Classifier: Programming Language :: Python :: 3.9
Classifier: Programming Language :: Python :: 3.10
Classifier: Programming Language :: Python :: 3.11
Requires-Dist: astunparse (>=1.6.3,<2.0.0) ; python_version < "3.9"
Requires-Dist: mkdocs (>=1.4.0,<2.0.0)
Requires-Dist: pymdown-extensions (>=6.3)
